<annotation>
	<folder>images</folder>
	<filename>face-212.jpg</filename>
	<path>/Users/jedakiller/Documents/data/images/face-212.jpg</path>
	<source>
		<database>Unknown</database>
	</source>
	<size>
		<width>1024</width>
		<height>682</height>
		<depth>3</depth>
	</size>
	<segmented>0</segmented>
	<object>
		<name>facew</name>
		<pose>Unspecified</pose>
		<truncated>0</truncated>
		<difficult>0</difficult>
		<bndbox>
			<xmin>160</xmin>
			<ymin>135</ymin>
			<xmax>273</xmax>
			<ymax>275</ymax>
		</bndbox>
	</object>
	<object>
		<name>facew</name>
		<pose>Unspecified</pose>
		<truncated>0</truncated>
		<difficult>0</difficult>
		<bndbox>
			<xmin>387</xmin>
			<ymin>133</ymin>
			<xmax>475</xmax>
			<ymax>272</ymax>
		</bndbox>
	</object>
	<object>
		<name>facew</name>
		<pose>Unspecified</pose>
		<truncated>0</truncated>
		<difficult>0</difficult>
		<bndbox>
			<xmin>257</xmin>
			<ymin>355</ymin>
			<xmax>377</xmax>
			<ymax>506</ymax>
		</bndbox>
	</object>
	<object>
		<name>facew</name>
		<pose>Unspecified</pose>
		<truncated>0</truncated>
		<difficult>0</difficult>
		<bndbox>
			<xmin>587</xmin>
			<ymin>94</ymin>
			<xmax>701</xmax>
			<ymax>238</ymax>
		</bndbox>
	</object>
	<object>
		<name>facew</name>
		<pose>Unspecified</pose>
		<truncated>0</truncated>
		<difficult>0</difficult>
		<bndbox>
			<xmin>732</xmin>
			<ymin>121</ymin>
			<xmax>859</xmax>
			<ymax>267</ymax>
		</bndbox>
	</object>
	<object>
		<name>facew</name>
		<pose>Unspecified</pose>
		<truncated>0</truncated>
		<difficult>0</difficult>
		<bndbox>
			<xmin>476</xmin>
			<ymin>305</ymin>
			<xmax>616</xmax>
			<ymax>489</ymax>
		</bndbox>
	</object>
	<object>
		<name>facew</name>
		<pose>Unspecified</pose>
		<truncated>0</truncated>
		<difficult>0</difficult>
		<bndbox>
			<xmin>690</xmin>
			<ymin>365</ymin>
			<xmax>790</xmax>
			<ymax>511</ymax>
		</bndbox>
	</object>
</annotation>
